wolfsoftware/list_availability_zones/__init__.py
wolfsoftware/list_availability_zones/availability_zones.py
wolfsoftware/list_availability_zones/cli.py
wolfsoftware/list_availability_zones/config.py
wolfsoftware/list_availability_zones/exceptions.py
wolfsoftware/list_availability_zones/globals.py
wolfsoftware/list_availability_zones/main.py
wolfsoftware/list_availability_zones/results.py
wolfsoftware.list_availability_zones-0.1.2.dist-info/LICENSE.md
wolfsoftware.list_availability_zones-0.1.2.dist-info/METADATA
wolfsoftware.list_availability_zones-0.1.2.dist-info/WHEEL
wolfsoftware.list_availability_zones-0.1.2.dist-info/entry_points.txt
wolfsoftware.list_availability_zones-0.1.2.dist-info/top_level.txt
wolfsoftware.list_availability_zones-0.1.2.dist-info/RECORD
