Metadata-Version: 2.1
Name: wolfsoftware.list-availability-zones
Version: 0.1.2
Summary: Generate a table of the availability zones your account is using.
Home-page: https://github.com/DevelopersToolbox/template-package-cli
Author: Wolf Software
Author-email: pypi@wolfsoftware.com
Project-URL: Source, https://github.com/AWSToolbox/list-availability-zones
Project-URL: Tracker, https://github.com/AWSToolbox/list-availability-zones/issues/
Project-URL: Documentation, https://github.com/AWSToolbox/list-availability-zones
Project-URL: Sponsor, https://github.com/sponsors/WolfSoftware
Classifier: Development Status :: 4 - Beta
Classifier: Environment :: Console
Classifier: Intended Audience :: System Administrators
Classifier: Intended Audience :: Other Audience
Classifier: License :: OSI Approved :: MIT License
Classifier: Programming Language :: Python :: 3
Classifier: Programming Language :: Python :: 3.9
Classifier: Programming Language :: Python :: 3.10
Classifier: Programming Language :: Python :: 3.11
Classifier: Programming Language :: Python :: 3.12
Classifier: Operating System :: OS Independent
Classifier: Topic :: Internet
Classifier: Topic :: Utilities
Requires-Python: >=3.9
License-File: LICENSE.md
Requires-Dist: botocore ==1.34.136
Requires-Dist: prettytable ==3.10.0
Requires-Dist: boto3 ==1.34.136
Requires-Dist: wolfsoftware.notify ==0.1.2
Requires-Dist: yaspin ==3.0.2
